README.md
package_info.json
setup.py
th2_grpc_act_uiframework_win_demo/__init__.py
th2_grpc_act_uiframework_win_demo/py.typed
th2_grpc_act_uiframework_win_demo/u_i_framework_act_service.py
th2_grpc_act_uiframework_win_demo/uiframework_win_demo.proto
th2_grpc_act_uiframework_win_demo/uiframework_win_demo_pb2.py
th2_grpc_act_uiframework_win_demo/uiframework_win_demo_pb2.pyi
th2_grpc_act_uiframework_win_demo/uiframework_win_demo_pb2_grpc.py
th2_grpc_act_uiframework_win_demo.egg-info/PKG-INFO
th2_grpc_act_uiframework_win_demo.egg-info/SOURCES.txt
th2_grpc_act_uiframework_win_demo.egg-info/dependency_links.txt
th2_grpc_act_uiframework_win_demo.egg-info/requires.txt
th2_grpc_act_uiframework_win_demo.egg-info/top_level.txt